trossen_ai_data_collection_ui/__init__.py
trossen_ai_data_collection_ui/__main__.py
trossen_ai_data_collection_ui/application.sh
trossen_ai_data_collection_ui/configs/calibration_config.yaml
trossen_ai_data_collection_ui/configs/robot/trossen_ai_robots.yaml
trossen_ai_data_collection_ui/configs/tasks.yaml
trossen_ai_data_collection_ui/post_install.py
trossen_ai_data_collection_ui/resources/__init__.py
trossen_ai_data_collection_ui/resources/app.py
trossen_ai_data_collection_ui/resources/app.ui
trossen_ai_data_collection_ui/resources/calibration_menu.py
trossen_ai_data_collection_ui/resources/calibration_menu.ui
trossen_ai_data_collection_ui/resources/no_video.jpg
trossen_ai_data_collection_ui/resources/trossen_ai.svg
trossen_ai_data_collection_ui/resources/trossen_ai_gui.png
trossen_ai_data_collection_ui/ui/__init__.py
trossen_ai_data_collection_ui/ui/main_window.py
trossen_ai_data_collection_ui/utils/__init__.py
trossen_ai_data_collection_ui/utils/constants.py
trossen_ai_data_collection_ui/utils/utils.py
trossen_ai_data_collection_ui/workers/__init__.py
trossen_ai_data_collection_ui/workers/recorder.py
trossen_ai_data_collection_ui/workers/yaml.py
trossen_ai_data_collection_ui-1.1.12.dist-info/LICENSE
trossen_ai_data_collection_ui-1.1.12.dist-info/METADATA
trossen_ai_data_collection_ui-1.1.12.dist-info/WHEEL
trossen_ai_data_collection_ui-1.1.12.dist-info/entry_points.txt
trossen_ai_data_collection_ui-1.1.12.dist-info/RECORD
