Metadata-Version: 2.1
Name: trossen-ai-data-collection-ui
Version: 1.1.12
Summary: 
License: BSD-3-Clause
Author: Shantanu Parab
Requires-Python: >=3.10,<3.13
Classifier: License :: OSI Approved :: BSD License
Classifier: Programming Language :: Python :: 3
Classifier: Programming Language :: Python :: 3.10
Classifier: Programming Language :: Python :: 3.11
Classifier: Programming Language :: Python :: 3.12
